LICENSE
README.md
setup.py
menfou/__init__.py
menfou/raf.py
menfou.egg-info/PKG-INFO
menfou.egg-info/SOURCES.txt
menfou.egg-info/dependency_links.txt
menfou.egg-info/top_level.txt