Metadata-Version: 1.0
Name: menfou
Version: 0.0.1
Summary: awesome package
Home-page: UNKNOWN
Author: someone incredibly awesome
Author-email: UNKNOWN
License: UNKNOWN
Platform: UNKNOWN
